prometheus_mailjet_exporter/__init__.py
prometheus_mailjet_exporter-0.1.0.dev1.dist-info/LICENSE
prometheus_mailjet_exporter-0.1.0.dev1.dist-info/METADATA
prometheus_mailjet_exporter-0.1.0.dev1.dist-info/WHEEL
prometheus_mailjet_exporter-0.1.0.dev1.dist-info/entry_points.txt
prometheus_mailjet_exporter-0.1.0.dev1.dist-info/top_level.txt
prometheus_mailjet_exporter-0.1.0.dev1.dist-info/RECORD
